prefect_jinja/__init__.py
prefect_jinja/_version.py
prefect_jinja/blocks.py
prefect_jinja/tasks.py
prefect_jinja-0.0.1.dist-info/LICENSE
prefect_jinja-0.0.1.dist-info/METADATA
prefect_jinja-0.0.1.dist-info/WHEEL
prefect_jinja-0.0.1.dist-info/top_level.txt
prefect_jinja-0.0.1.dist-info/RECORD
